pycobol2parquet/__init__.py
pycobol2parquet/convert.py
pycobol2parquet-0.0.3.dist-info/LICENSE
pycobol2parquet-0.0.3.dist-info/METADATA
pycobol2parquet-0.0.3.dist-info/WHEEL
pycobol2parquet-0.0.3.dist-info/top_level.txt
pycobol2parquet-0.0.3.dist-info/RECORD
