Metadata-Version: 2.1
Name: pycobol2parquet
Version: 0.0.3
Summary: A Python library to convert COBOL ebcdic file to parquet format based on copybook
Home-page: https://github.com/jasonli-lijie/pycobol2parquet
Download-URL: https://github.com/user/reponame/archive/v_01.tar.gz
Author: Jason Li
Author-email: niomobileapp@gmail.com
License: MIT
Project-URL: Bug Tracker, https://github.com/jasonli-lijie/pycobol2parquet/issues
Keywords: COBOL,parquet
Classifier: Development Status :: 3 - Alpha
Classifier: Intended Audience :: Developers
Classifier: Topic :: Software Development :: Build Tools
Classifier: License :: OSI Approved :: MIT License
Classifier: Programming Language :: Python :: 3
Classifier: Programming Language :: Python :: 3.6
Classifier: Programming Language :: Python :: 3.7
Classifier: Programming Language :: Python :: 3.8
Classifier: Programming Language :: Python :: 3.9
Classifier: Programming Language :: Python :: 3.10
License-File: LICENSE
Requires-Dist: pyarrow
